simpleconf/__init__.py
simpleconf/base.py
simpleconf/config.py
simple_dataclass_configuration-0.1.2.dist-info/LICENSE
simple_dataclass_configuration-0.1.2.dist-info/METADATA
simple_dataclass_configuration-0.1.2.dist-info/WHEEL
simple_dataclass_configuration-0.1.2.dist-info/RECORD
