Metadata-Version: 2.1
Name: simple-dataclass-configuration
Version: 0.1.2
Summary: 
Home-page: https://github.com/zimolab/simple-conf
License: MIT
Author: zimolab
Author-email: zimolab@aliyun.com
Requires-Python: >=3.10,<4.0
Classifier: License :: OSI Approved :: MIT License
Classifier: Programming Language :: Python :: 3
Classifier: Programming Language :: Python :: 3.10
Classifier: Programming Language :: Python :: 3.11
Classifier: Programming Language :: Python :: 3.12
Requires-Dist: marshmallow (>=3.20.2,<4.0.0)
Requires-Dist: marshmallow-dataclass[enum,union] (>=8.6.0,<9.0.0)
Requires-Dist: pyyaml (>=6.0.1,<7.0.0)
Requires-Dist: tomli (>=2.0.1,<3.0.0)
Requires-Dist: tomli-w (>=1.0.0,<2.0.0)
Project-URL: Documentation, https://github.com/zimolab/simple-conf
Project-URL: Repository, https://github.com/zimolab/simple-conf
